{
  "barcode": "3166296550432",
  "name": "Moulin 5 Baies",
  "brands": "Ducros",
  "categories": "Plant-based foods and beverages, Plant-based foods, Condiments, Spices, Peppers, Groceries",
  "countries_sold": "France",
  "nutri_score": "e",
  "green_score_letter": null,
  "green_score_final": null,
  "carbon_impact_per_100g": null,
  "carbon_equiv_distance": "815 g CO₂e per 100g of product",
  "serving_size": {
    "quantity": 1.0,
    "unit": "g"
  },
  "quantity": {
    "quantity": 26.0,
    "unit": "g"
  },
  "packaging": null,
  "labels": null,
  "origin": null,
  "manufacturing_places": null,
  "stores": "carrefour.fr",
  "allergens": null,
  "ingredients_text": null,
  "ingredients_structured": [
    {
      "ingredient": "Black pepper",
      "percentage": "58.3% (estimate)"
    },
    {
      "ingredient": "Coriander seed",
      "percentage": "20.8% (estimate)"
    },
    {
      "ingredient": "Pink peppercorn",
      "percentage": "10.4% (estimate)"
    },
    {
      "ingredient": "White pepper",
      "percentage": "5.2% (estimate)"
    },
    {
      "ingredient": "Allspice",
      "percentage": "2.6% (estimate)"
    },
    {
      "ingredient": "Green pepper",
      "percentage": "2.6% (estimate)"
    }
  ],
  "conservation_conditions": null,
  "customer_service": null,
  "nutrients_100g": {},
  "is_valid": true
}